{
  "tag": "cluster",
  "@{http://www.w3.org/2001/XMLSchema-instance}noNamespaceSchemaLocation": "cluster.xsd",
  "@origin": "-945 -775",
  "@size": "1580 1420",
  "@minimapBoundsMin": "-840 -700",
  "@minimapBoundsMax": "460 600",
  "@minimapHeightRangeEnabled": "true",
  "@minimapHeightRange": "0 12",
  "@minimapBaseLevelEnabled": "true",
  "@minimapBaseLevel": "6",
  "@minimapMaterialPreset": "Avalon",
  "@oceanflow": "0.05",
  "@oceanflowspeed": "0.01",
  "@oceananimspeed": "0.4",
  "templateinstance": [
    {
      "@id": "instanceslot_00",
      "@ref": "ROAD_C_M2_S6_P6",
      "@pos": "-390 0 -130",
      "@rot": "180",
      "activelayer": [
        {
          "@id": "Layer_02"
        },
        {
          "@id": "Layer_04"
        },
        {
          "@id": "Layer_06"
        },
        {
          "@id": "Layer_08"
        },
        {
          "@id": "Layer_10"
        },
        {
          "@id": "Layer_12"
        },
        {
          "@id": "Layer_13"
        },
        {
          "@id": "Layer_15"
        }
      ]
    },
    {
      "@id": "instanceslot_01",
      "@ref": "M_FR_ROAD_Medium_Sleeve_01",
      "@pos": "-565 0 -275",
      "@rot": "270",
      "activelayer": [
        {
          "@id": "Layer_04"
        },
        {
          "@id": "Layer_07"
        }
      ]
    },
    {
      "@id": "instanceslot_02",
      "@ref": "S_FR_ROAD_Portal_01",
      "@pos": "-485 0 305",
      "activelayer": [
        {
          "@id": "Layer_03"
        }
      ]
    },
    {
      "@id": "instanceslot_03",
      "@ref": "S_FR_ROAD_PVE_Encounter_01",
      "@pos": "-485 0 -475",
      "@rot": "180",
      "activelayer": [
        {
          "@id": "Layer_04"
        },
        {
          "@id": "Layer_08"
        }
      ]
    },
    {
      "@id": "instanceslot_04",
      "@ref": "S_FR_ROAD_RES_Clearing_01",
      "@pos": "195 0 -455",
      "@rot": "270",
      "activelayer": [
        {
          "@id": "Layer_03"
        },
        {
          "@id": "Layer_21"
        }
      ]
    },
    {
      "@id": "instanceslot_05",
      "@ref": "S_FR_ROAD_Portal_01",
      "@pos": "95 0 -575",
      "@rot": "180",
      "activelayer": [
        {
          "@id": "Layer_03"
        }
      ]
    },
    {
      "@id": "instanceslot_06",
      "@ref": "S_FR_ROAD_RES_Clearing_01",
      "@pos": "-585 0 25",
      "@rot": "90",
      "activelayer": [
        {
          "@id": "Layer_07"
        },
        {
          "@id": "Layer_21"
        }
      ]
    },
    {
      "@id": "instanceslot_07",
      "@ref": "M_FR_ROAD_PVE_GROUP_01",
      "@pos": "-165 0 25",
      "@rot": "180",
      "activelayer": [
        {
          "@id": "Layer_01"
        }
      ]
    },
    {
      "@id": "instanceslot_08",
      "@ref": "M_FR_ROAD_PVE_GROUP_01",
      "@pos": "-565 0 -275",
      "@rot": "90",
      "activelayer": [
        {
          "@id": "Layer_02"
        }
      ]
    },
    {
      "@id": "instanceslot_09",
      "@ref": "M_FR_ROAD_Medium_Sleeve_01",
      "@pos": "-165 0 25",
      "@rot": "90",
      "activelayer": [
        {
          "@id": "Layer_04"
        },
        {
          "@id": "Layer_07"
        }
      ]
    },
    {
      "@id": "instanceslot_10",
      "@ref": "S_FR_ROAD_DNG_GROUP_Entrance_01",
      "@pos": "-425 0 105",
      "@rot": "270",
      "activelayer": [
        {
          "@id": "Layer_05"
        },
        {
          "@id": "Layer_09"
        }
      ]
    },
    {
      "@id": "instanceslot_11",
      "@ref": "S_FR_ROAD_RES_Clearing_01",
      "@pos": "-225 0 -355",
      "@rot": "180",
      "activelayer": [
        {
          "@id": "Layer_02"
        },
        {
          "@id": "Layer_22"
        }
      ]
    },
    {
      "@id": "instanceslot_12",
      "@ref": "S_FR_ROAD_RES_Clearing_01",
      "@pos": "175 0 -135",
      "@rot": "90",
      "activelayer": [
        {
          "@id": "Layer_02"
        },
        {
          "@id": "Layer_22"
        }
      ]
    },
    {
      "@id": "instanceslot_13",
      "@ref": "S_FR_ROAD_Portal_01",
      "@pos": "95 0 105",
      "@rot": "180",
      "activelayer": [
        {
          "@id": "Layer_03"
        }
      ]
    },
    {
      "@id": "instanceslot_14",
      "@ref": "S_FR_ROAD_Portal_01",
      "@pos": "-485 0 -575",
      "activelayer": [
        {
          "@id": "Layer_03"
        }
      ]
    },
    {
      "@id": "instanceslot_15",
      "@ref": "S_FR_ROAD_Portal_01",
      "@pos": "-25 0 -235",
      "activelayer": [
        {
          "@id": "Layer_03"
        }
      ]
    },
    {
      "@id": "instanceslot_16",
      "@ref": "S_FR_ROAD_Portal_01",
      "@pos": "-85 0 445",
      "@rot": "90",
      "activelayer": [
        {
          "@id": "Layer_03"
        }
      ]
    }
  ]
}